setup.py
udacity_aws_distributions/Binomialdistribution.py
udacity_aws_distributions/Gaussiandistribution.py
udacity_aws_distributions/Generaldistribution.py
udacity_aws_distributions/__init__.py
udacity_aws_distributions.egg-info/PKG-INFO
udacity_aws_distributions.egg-info/SOURCES.txt
udacity_aws_distributions.egg-info/dependency_links.txt
udacity_aws_distributions.egg-info/not-zip-safe
udacity_aws_distributions.egg-info/top_level.txt